{
  "nodes": [
    {
      "id": "n1",
      "label": "Draw two habitats and the different living things in each",
      "fillcolor": "lightblue",
      "shape": "hexagon"
    },
    {
      "id": "n2",
      "label": "Lush green forest with tall trees and shrubs",
      "fillcolor": "#fffdd0",
      "shape": "rectangle"
    },
    {
      "id": "n3",
      "label": "Variety of forest animals like squirrels and deer",
      "fillcolor": "#fffdd0",
      "shape": "rectangle"
    },
    {
      "id": "n4",
      "label": "Vibrant pond habitat with lily pads, reeds",
      "fillcolor": "#fffdd0",
      "shape": "rectangle"
    },
    {
      "id": "n5",
      "label": "Fish, frogs, and aquatic insects in pond habitat",
      "fillcolor": "#fffdd0",
      "shape": "rectangle"
    },
    {
      "id": "n6",
      "label": "Identifies and illustrates land and water habitats",
      "fillcolor": "palegreen",
      "shape": "roundbox"
    },
    {
      "id": "n7",
      "label": "Draws and labels different plants in each habitat",
      "fillcolor": "palegreen",
      "shape": "roundbox"
    },
    {
      "id": "n8",
      "label": "Draws and labels different animals in each habitat",
      "fillcolor": "palegreen",
      "shape": "roundbox"
    },
    {
      "id": "n9",
      "label": "Illustrates and compares plant and animal differences",
      "fillcolor": "palegreen",
      "shape": "roundbox"
    },
    {
      "id": "n10",
      "label": "Identifies patterns in living things across habitats",
      "fillcolor": "palegreen",
      "shape": "roundbox"
    }
  ],
  "edges": [
    [
      "n1",
      "n2"
    ],
    [
      "n1",
      "n3"
    ],
    [
      "n1",
      "n4"
    ],
    [
      "n1",
      "n5"
    ],
    [
      "n2",
      "n6"
    ],
    [
      "n2",
      "n7"
    ],
    [
      "n3",
      "n8"
    ],
    [
      "n4",
      "n9"
    ],
    [
      "n5",
      "n10"
    ]
  ]
}