{
  "nodes": [
    {
      "id": "n1",
      "label": "Draw two habitats and the different living things in each",
      "fillcolor": "lightblue",
      "shape": "hexagon"
    },
    {
      "id": "n2",
      "label": "Forest with trees and animals",
      "fillcolor": "#fffdd0",
      "shape": "rectangle"
    },
    {
      "id": "n3",
      "label": "Water habitat with fish and trees",
      "fillcolor": "#fffdd0",
      "shape": "rectangle"
    },
    {
      "id": "n4",
      "label": "Elephant near both habitats",
      "fillcolor": "#fffdd0",
      "shape": "rectangle"
    },
    {
      "id": "n5",
      "label": "Land and water represented",
      "fillcolor": "palegreen",
      "shape": "roundbox"
    },
    {
      "id": "n6",
      "label": "Mixed elements from both habitats",
      "fillcolor": "lightcoral",
      "shape": "diamond"
    },
    {
      "id": "n7",
      "label": "Inclusion of diverse plants and animals",
      "fillcolor": "lightcoral",
      "shape": "diamond"
    },
    {
      "id": "n8",
      "label": "Distinguish which animals/plants belong in each habitat",
      "fillcolor": "#f28e8e",
      "shape": "parallelogram"
    },
    {
      "id": "n9",
      "label": "Clarify unique species to respective habitats",
      "fillcolor": "#f28e8e",
      "shape": "parallelogram"
    }
  ],
  "edges": [
    [
      "n1",
      "n2"
    ],
    [
      "n1",
      "n3"
    ],
    [
      "n1",
      "n4"
    ],
    [
      "n2",
      "n5"
    ],
    [
      "n3",
      "n6"
    ],
    [
      "n4",
      "n7"
    ],
    [
      "n6",
      "n8"
    ],
    [
      "n7",
      "n9"
    ]
  ]
}