{
  "nodes": [
    {
      "id": "n1",
      "label": "Draw animals in their habitats with labels (e.g., fish in water).",
      "fillcolor": "lightblue",
      "shape": "hexagon"
    },
    {
      "id": "n2",
      "label": "Ocean scene with fish, seaweed, turtle, flower, and bird.",
      "fillcolor": "#fffdd0",
      "shape": "rectangle"
    },
    {
      "id": "n3",
      "label": "Fish in water",
      "fillcolor": "palegreen",
      "shape": "roundbox"
    },
    {
      "id": "n4",
      "label": "Seaweed in ocean",
      "fillcolor": "palegreen",
      "shape": "roundbox"
    },
    {
      "id": "n5",
      "label": "Turtle on sand",
      "fillcolor": "lightcoral",
      "shape": "diamond"
    },
    {
      "id": "n6",
      "label": "Flower on beach without context",
      "fillcolor": "lightcoral",
      "shape": "diamond"
    },
    {
      "id": "n7",
      "label": "Bird flying in sky",
      "fillcolor": "palegreen",
      "shape": "roundbox"
    },
    {
      "id": "n8",
      "label": "Turtles live in water and land; depict environment use.",
      "fillcolor": "#f28e8e",
      "shape": "parallelogram"
    },
    {
      "id": "n9",
      "label": "Explain flower's role or remove if out of context",
      "fillcolor": "#f28e8e",
      "shape": "parallelogram"
    }
  ],
  "edges": [
    [
      "n1",
      "n2"
    ],
    [
      "n2",
      "n3"
    ],
    [
      "n2",
      "n4"
    ],
    [
      "n2",
      "n5"
    ],
    [
      "n2",
      "n6"
    ],
    [
      "n2",
      "n7"
    ],
    [
      "n5",
      "n8"
    ],
    [
      "n6",
      "n9"
    ]
  ]
}