{
  "nodes": [
    {
      "id": "n1",
      "label": "Draw reversible changes (ice melting)",
      "fillcolor": "lightblue",
      "shape": "hexagon"
    },
    {
      "id": "n2",
      "label": "Child's drawing shows: a square block labeled ‘ice’, wavy lines labeled ‘water’, arrows misdirected or incorrectly sequenced",
      "fillcolor": "#fffdd0",
      "shape": "rectangle"
    },
    {
      "id": "n3",
      "label": "Titles drawing with 'Water Fun'",
      "fillcolor": "#fffdd0",
      "shape": "rectangle"
    },
    {
      "id": "n4",
      "label": "Correctly represents ice as solid",
      "fillcolor": "palegreen",
      "shape": "roundbox"
    },
    {
      "id": "n5",
      "label": "Correctly represents water as liquid",
      "fillcolor": "palegreen",
      "shape": "roundbox"
    },
    {
      "id": "n6",
      "label": "Misdirected or incorrect sequencing of arrows",
      "fillcolor": "lightcoral",
      "shape": "diamond"
    },
    {
      "id": "n7",
      "label": "Incorrect/missing labeling of cooling step",
      "fillcolor": "lightcoral",
      "shape": "diamond"
    },
    {
      "id": "n8",
      "label": "Clarify arrows to show the process from ice to water and back",
      "fillcolor": "#f28e8e",
      "shape": "parallelogram"
    },
    {
      "id": "n9",
      "label": "Add labels for cooling step to complete cycle",
      "fillcolor": "#f28e8e",
      "shape": "parallelogram"
    },
    {
      "id": "n10",
      "label": "Explain that the change is reversible with a caption",
      "fillcolor": "#f28e8e",
      "shape": "parallelogram"
    }
  ],
  "edges": [
    [
      "n1",
      "n2"
    ],
    [
      "n1",
      "n3"
    ],
    [
      "n2",
      "n4"
    ],
    [
      "n2",
      "n5"
    ],
    [
      "n2",
      "n6"
    ],
    [
      "n2",
      "n7"
    ],
    [
      "n6",
      "n8"
    ],
    [
      "n7",
      "n9"
    ],
    [
      "n3",
      "n10"
    ]
  ]
}