{
  "nodes": [
    {
      "id": "n1",
      "label": "Draw animals in their habitats with labels (e.g., fish in water).",
      "fillcolor": "lightblue",
      "shape": "hexagon"
    },
    {
      "id": "n2",
      "label": "Green frog on a lilypad labeled 'pond'",
      "fillcolor": "#fffdd0",
      "shape": "rectangle"
    },
    {
      "id": "n3",
      "label": "Fish swimming with bubbles around it",
      "fillcolor": "#fffdd0",
      "shape": "rectangle"
    },
    {
      "id": "n4",
      "label": "Deer under trees labeled 'forest'",
      "fillcolor": "#fffdd0",
      "shape": "rectangle"
    },
    {
      "id": "n5",
      "label": "Small bird in the tree branches",
      "fillcolor": "#fffdd0",
      "shape": "rectangle"
    },
    {
      "id": "n6",
      "label": "Bright yellow sun in the sky",
      "fillcolor": "#fffdd0",
      "shape": "rectangle"
    },
    {
      "id": "n7",
      "label": "Understands that frogs live in ponds",
      "fillcolor": "palegreen",
      "shape": "roundbox"
    },
    {
      "id": "n8",
      "label": "Understands that fish live in water",
      "fillcolor": "palegreen",
      "shape": "roundbox"
    },
    {
      "id": "n9",
      "label": "Understands that deer live in forests",
      "fillcolor": "palegreen",
      "shape": "roundbox"
    },
    {
      "id": "n10",
      "label": "Understands birds can perch in trees",
      "fillcolor": "palegreen",
      "shape": "roundbox"
    },
    {
      "id": "n11",
      "label": "Misunderstanding: Drawing lacks labels for sunlight as a need for plants",
      "fillcolor": "lightcoral",
      "shape": "diamond"
    },
    {
      "id": "n12",
      "label": "Include labels for sunlight to show its importance for plants",
      "fillcolor": "#f28e8e",
      "shape": "parallelogram"
    }
  ],
  "edges": [
    [
      "n1",
      "n2"
    ],
    [
      "n1",
      "n3"
    ],
    [
      "n1",
      "n4"
    ],
    [
      "n1",
      "n5"
    ],
    [
      "n1",
      "n6"
    ],
    [
      "n2",
      "n7"
    ],
    [
      "n3",
      "n8"
    ],
    [
      "n4",
      "n9"
    ],
    [
      "n5",
      "n10"
    ],
    [
      "n6",
      "n11"
    ],
    [
      "n11",
      "n12"
    ]
  ]
}